setup.py
git_svnmodule/__init__.py
git_svnmodule/config.py
git_svnmodule/main.py
git_svnmodule/subp.py
git_svnmodule/svn.py
git_svnmodule.egg-info/PKG-INFO
git_svnmodule.egg-info/SOURCES.txt
git_svnmodule.egg-info/dependency_links.txt
git_svnmodule.egg-info/entry_points.txt
git_svnmodule.egg-info/top_level.txt