Metadata-Version: 1.1
Name: git-svnmodule
Version: 0.1.2
Summary: use SVN repositories like Git submodules
Home-page: https://github.com/NiklasRosenstein/git-svnmodule
Author: Niklas Rosenstein
Author-email: rosensteinniklas@gmail.com
License: UNKNOWN
Keywords: git submodules svn
Platform: UNKNOWN
Classifier: Development Status :: 3 - Alpha
Classifier: Intended Audience :: Developers
Classifier: Topic :: Software Development :: Version Control
